odoo/addons/document_page_project/README.rst
odoo/addons/document_page_project/__init__.py
odoo/addons/document_page_project/__manifest__.py
odoo/addons/document_page_project/i18n/document_page_project.pot
odoo/addons/document_page_project/i18n/es.po
odoo/addons/document_page_project/i18n/hr.po
odoo/addons/document_page_project/i18n/it.po
odoo/addons/document_page_project/i18n/pt_BR.po
odoo/addons/document_page_project/i18n/sl.po
odoo/addons/document_page_project/models/__init__.py
odoo/addons/document_page_project/models/document_page.py
odoo/addons/document_page_project/models/project_project.py
odoo/addons/document_page_project/readme/CONTRIBUTORS.rst
odoo/addons/document_page_project/readme/DESCRIPTION.rst
odoo/addons/document_page_project/readme/USAGE.rst
odoo/addons/document_page_project/static/description/icon.png
odoo/addons/document_page_project/static/description/index.html
odoo/addons/document_page_project/views/document_page_views.xml
odoo/addons/document_page_project/views/project_project_views.xml
odoo12_addon_document_page_project-12.0.1.0.0.99.dev13.dist-info/METADATA
odoo12_addon_document_page_project-12.0.1.0.0.99.dev13.dist-info/WHEEL
odoo12_addon_document_page_project-12.0.1.0.0.99.dev13.dist-info/top_level.txt
odoo12_addon_document_page_project-12.0.1.0.0.99.dev13.dist-info/RECORD
